<?xml version="1.0" encoding="UTF-8"?><record_update>
    <sys_dictionary action="DELETE" element="u____none___" table="x_snc_linkedin_r_0_1713550269116">
        <active>true</active>
        <array>false</array>
        <attributes>edge_encryption_enabled=true,import_attribute_name=-- None --</attributes>
        <audit>false</audit>
        <calculation/>
        <choice>0</choice>
        <choice_field/>
        <choice_table/>
        <column_label>-- None --</column_label>
        <comments/>
        <create_roles/>
        <default_value/>
        <defaultsort/>
        <delete_roles/>
        <dependent/>
        <dependent_on_field/>
        <display>false</display>
        <dynamic_creation>false</dynamic_creation>
        <dynamic_creation_script/>
        <dynamic_default_value/>
        <dynamic_ref_qual/>
        <element>u____none___</element>
        <element_reference>false</element_reference>
        <foreign_database/>
        <formula/>
        <function_definition/>
        <function_field>false</function_field>
        <internal_type display_value="String">string</internal_type>
        <mandatory>false</mandatory>
        <max_length>40</max_length>
        <name>x_snc_linkedin_r_0_1713550269116</name>
        <next_element/>
        <primary>false</primary>
        <read_only>false</read_only>
        <read_roles/>
        <reference/>
        <reference_cascade_rule/>
        <reference_floats>false</reference_floats>
        <reference_key/>
        <reference_qual/>
        <reference_qual_condition/>
        <reference_type/>
        <spell_check>false</spell_check>
        <staged>false</staged>
        <sys_class_name>sys_dictionary</sys_class_name>
        <sys_created_by>earl.duque</sys_created_by>
        <sys_created_on>2024-04-19 18:11:15</sys_created_on>
        <sys_id>ecab64a393a10a10b653ffbd1dba100d</sys_id>
        <sys_name>-- None --</sys_name>
        <sys_package display_value="LinkedIn Recruiter Message Generator" source="x_snc_linkedin_r_0">3c4b6c6393a10a10b653ffbd1dba10e6</sys_package>
        <sys_policy/>
        <sys_scope display_value="LinkedIn Recruiter Message Generator">3c4b6c6393a10a10b653ffbd1dba10e6</sys_scope>
        <sys_update_name>sys_dictionary_x_snc_linkedin_r_0_1713550269116_u____none___</sys_update_name>
        <sys_updated_by>earl.duque</sys_updated_by>
        <sys_updated_on>2024-04-19 18:11:15</sys_updated_on>
        <table_reference>false</table_reference>
        <text_index>false</text_index>
        <unique>false</unique>
        <use_dependent_field>false</use_dependent_field>
        <use_dynamic_default>false</use_dynamic_default>
        <use_reference_qualifier>simple</use_reference_qualifier>
        <virtual>false</virtual>
        <virtual_type>script</virtual_type>
        <widget/>
        <write_roles/>
        <xml_view>false</xml_view>
    </sys_dictionary>
    <sys_update_version action="INSERT_OR_UPDATE">
        <action>DELETE</action>
        <application display_value="LinkedIn Recruiter Message Generator">3c4b6c6393a10a10b653ffbd1dba10e6</application>
        <file_path/>
        <instance_id>13d96523db2ee594387021c40596192b</instance_id>
        <instance_name>earlio</instance_name>
        <name>sys_dictionary_x_snc_linkedin_r_0_1713550269116_u____none___</name>
        <payload><![CDATA[<?xml version="1.0" encoding="UTF-8"?><record_update><sys_dictionary action="INSERT_OR_UPDATE" element="u____none___" table="x_snc_linkedin_r_0_1713550269116"><active>true</active><array>false</array><attributes>edge_encryption_enabled=true,import_attribute_name=-- None --</attributes><audit>false</audit><calculation/><choice>0</choice><choice_field/><choice_table/><column_label>-- None --</column_label><comments/><create_roles/><default_value/><defaultsort/><delete_roles/><dependent/><dependent_on_field/><display>false</display><dynamic_creation>false</dynamic_creation><dynamic_creation_script/><dynamic_default_value/><dynamic_ref_qual/><element>u____none___</element><element_reference>false</element_reference><foreign_database/><formula/><function_definition/><function_field>false</function_field><internal_type display_value="String">string</internal_type><mandatory>false</mandatory><max_length>40</max_length><name>x_snc_linkedin_r_0_1713550269116</name><next_element/><primary>false</primary><read_only>false</read_only><read_roles/><reference/><reference_cascade_rule/><reference_floats>false</reference_floats><reference_key/><reference_qual/><reference_qual_condition/><reference_type/><spell_check>false</spell_check><staged>false</staged><sys_class_name>sys_dictionary</sys_class_name><sys_created_by>earl.duque</sys_created_by><sys_created_on>2024-04-19 18:11:15</sys_created_on><sys_id>ecab64a393a10a10b653ffbd1dba100d</sys_id><sys_name>-- None --</sys_name><sys_package display_value="LinkedIn Recruiter Message Generator" source="x_snc_linkedin_r_0">3c4b6c6393a10a10b653ffbd1dba10e6</sys_package><sys_policy/><sys_scope display_value="LinkedIn Recruiter Message Generator">3c4b6c6393a10a10b653ffbd1dba10e6</sys_scope><sys_update_name>sys_dictionary_x_snc_linkedin_r_0_1713550269116_u____none___</sys_update_name><sys_updated_by>earl.duque</sys_updated_by><sys_updated_on>2024-04-19 18:11:15</sys_updated_on><table_reference>false</table_reference><text_index>false</text_index><unique>false</unique><use_dependent_field>false</use_dependent_field><use_dynamic_default>false</use_dynamic_default><use_reference_qualifier>simple</use_reference_qualifier><virtual>false</virtual><virtual_type>script</virtual_type><widget/><write_roles/><xml_view>false</xml_view></sys_dictionary></record_update>]]></payload>
        <payload_hash>-1280925524</payload_hash>
        <record_name>Linkedin R 0 1713550269116.-- None --</record_name>
        <reverted_from/>
        <source>304bac6393a10a10b653ffbd1dba105b</source>
        <source_table>sys_update_set</source_table>
        <state>previous</state>
        <sys_created_by>earl.duque</sys_created_by>
        <sys_created_on>2024-04-19 18:11:15</sys_created_on>
        <sys_id>f4ab64a393a10a10b653ffbd1dba1025</sys_id>
        <sys_mod_count>0</sys_mod_count>
        <sys_recorded_at>18ef78e33390000001</sys_recorded_at>
        <sys_updated_by>earl.duque</sys_updated_by>
        <sys_updated_on>2024-04-19 18:11:15</sys_updated_on>
        <type>Dictionary</type>
        <update_guid>3cab64a318a10a10430b7db141c13924</update_guid>
        <update_guid_history>3cab64a318a10a10430b7db141c13924:-1280925524</update_guid_history>
    </sys_update_version>
    <sys_metadata_delete action="INSERT_OR_UPDATE">
        <sys_audit_delete/>
        <sys_class_name>sys_metadata_delete</sys_class_name>
        <sys_created_by>earl.duque</sys_created_by>
        <sys_created_on>2024-04-19 18:15:25</sys_created_on>
        <sys_db_object display_value="" name="sys_dictionary">sys_dictionary</sys_db_object>
        <sys_id>a5a1f10585864e03ac53e7b5a48af029</sys_id>
        <sys_metadata>ecab64a393a10a10b653ffbd1dba100d</sys_metadata>
        <sys_mod_count>0</sys_mod_count>
        <sys_name>-- None --</sys_name>
        <sys_package display_value="LinkedIn Recruiter Message Generator" source="x_snc_linkedin_r_0">3c4b6c6393a10a10b653ffbd1dba10e6</sys_package>
        <sys_parent display_value="">e8ab24a393a10a10b653ffbd1dba10e9</sys_parent>
        <sys_policy/>
        <sys_scope display_value="LinkedIn Recruiter Message Generator">3c4b6c6393a10a10b653ffbd1dba10e6</sys_scope>
        <sys_scope_delete display_value="">89ab73c02e3e4a028e8cceaace89fe31</sys_scope_delete>
        <sys_update_name>sys_dictionary_x_snc_linkedin_r_0_1713550269116_u____none___</sys_update_name>
        <sys_update_version display_value="sys_dictionary_x_snc_linkedin_r_0_1713550269116_u____none___">f4ab64a393a10a10b653ffbd1dba1025</sys_update_version>
        <sys_updated_by>earl.duque</sys_updated_by>
        <sys_updated_on>2024-04-19 18:15:25</sys_updated_on>
    </sys_metadata_delete>
</record_update>
